odoo/addons/stock_release_channel_depot/README.rst
odoo/addons/stock_release_channel_depot/__init__.py
odoo/addons/stock_release_channel_depot/__manifest__.py
odoo/addons/stock_release_channel_depot/i18n/it.po
odoo/addons/stock_release_channel_depot/i18n/stock_release_channel_depot.pot
odoo/addons/stock_release_channel_depot/l18n/fr.po
odoo/addons/stock_release_channel_depot/l18n/stock_release_channel_depot.pot
odoo/addons/stock_release_channel_depot/models/__init__.py
odoo/addons/stock_release_channel_depot/models/release_channel.py
odoo/addons/stock_release_channel_depot/models/stock_picking.py
odoo/addons/stock_release_channel_depot/readme/CONTRIBUTORS.rst
odoo/addons/stock_release_channel_depot/readme/DESCRIPTION.rst
odoo/addons/stock_release_channel_depot/static/description/icon.png
odoo/addons/stock_release_channel_depot/static/description/index.html
odoo/addons/stock_release_channel_depot/views/stock_picking.xml
odoo/addons/stock_release_channel_depot/views/stock_release_channel_views.xml
odoo_addon_stock_release_channel_depot-16.0.1.0.0.4.dist-info/METADATA
odoo_addon_stock_release_channel_depot-16.0.1.0.0.4.dist-info/WHEEL
odoo_addon_stock_release_channel_depot-16.0.1.0.0.4.dist-info/top_level.txt
odoo_addon_stock_release_channel_depot-16.0.1.0.0.4.dist-info/RECORD
